polysplit/__init__.py
polysplit/polysplit.py
polysplit/docs/conf.py
polysplit/tests/__init__.py
polysplit/tests/test_polysplit.py
polysplit-0.1.3.dist-info/LICENSE
polysplit-0.1.3.dist-info/METADATA
polysplit-0.1.3.dist-info/WHEEL
polysplit-0.1.3.dist-info/top_level.txt
polysplit-0.1.3.dist-info/RECORD
