Metadata-Version: 2.1
Name: polysplit
Version: 0.1.3
Summary: A Python library implementing a method for splitting a polygon into regions
Author-email: Dmitrii Zakharov <d.zakharov@columbia.edu>
License: MIT License
Project-URL: repository, https://github.com/r1p71d3/polysplit
Classifier: Development Status :: 2 - Pre-Alpha
Classifier: Programming Language :: Python :: Implementation :: CPython
Classifier: Programming Language :: Python :: Implementation :: PyPy
Classifier: Programming Language :: Python :: 3
Classifier: Programming Language :: Python :: 3.7
Classifier: Programming Language :: Python :: 3.8
Classifier: Programming Language :: Python :: 3.9
Classifier: Programming Language :: Python :: 3.10
Classifier: Programming Language :: Python :: 3.11
Requires-Python: >=3.7
License-File: LICENSE
Requires-Dist: matplotlib
Requires-Dist: shapely
Requires-Dist: numpy
Requires-Dist: scikit-learn (>=1.2.1)
Requires-Dist: scikit-learn-extra (>=0.2.0)
Requires-Dist: networkx
Provides-Extra: develop
Requires-Dist: black (>=22) ; extra == 'develop'
Requires-Dist: bump2version (>=1.0.0) ; extra == 'develop'
Requires-Dist: check-manifest ; extra == 'develop'
Requires-Dist: flake8 (>=3.7.8) ; extra == 'develop'
Requires-Dist: flake8-black (>=0.2.1) ; extra == 'develop'
Requires-Dist: flake8-pyproject ; extra == 'develop'
Requires-Dist: mypy ; extra == 'develop'
Requires-Dist: pytest (>=4.3.0) ; extra == 'develop'
Requires-Dist: pytest-cov (>=2.6.1) ; extra == 'develop'
Requires-Dist: twine ; extra == 'develop'
Requires-Dist: wheel ; extra == 'develop'
Requires-Dist: matplotlib ; extra == 'develop'
Requires-Dist: shapely ; extra == 'develop'
Requires-Dist: numpy ; extra == 'develop'
Requires-Dist: scikit-learn (>=1.2.1) ; extra == 'develop'
Requires-Dist: scikit-learn-extra (>=0.2.0) ; extra == 'develop'
Requires-Dist: networkx ; extra == 'develop'
